Workbook

Sheet products_cleaned
A1: product_id | B1: product_name | C1: category | D1: unit_price | E1: cost_price
A2: P001 | B2: Wireless Mouse | C2: Electronics | D2: 599 | E2: 345.86
A3: P002 | B3: Bluetooth Headphones | C3: Electronics | D3: 1999 | E3: 1330.49
A4: P003 | B4: Smart Watch | C4: Electronics | D4: 3499 | E4: 2336.35
A5: P004 | B5: USB-C Hub | C5: Electronics | D5: 1299 | E5: 971.39
A6: P005 | B6: External SSD | C6: Electronics | D6: 4599 | E6: 2638.02
A7: P006 | B7: Keyboard | C7: Electronics | D7: 899 | E7: 540.62
A8: P007 | B8: Power Bank | C8: Electronics | D8: 1499 | E8: 1031.67
A9: P008 | B9: Laptop Stand | C9: Electronics | D9: 1199 | E9: 812.93
A10: P009 | B10: Cotton T-Shirt | C10: Fashion | D10: 499 | E10: 364.36
A11: P010 | B11: Denim Jeans | C11: Fashion | D11: 1799 | E11: 1216.12
A12: P011 | B12: Travel Backpack | C12: Fashion | D12: 1599 | E12: 1148.12
A13: P012 | B13: Casual Shirt | C13: Fashion | D13: 999 | E13: 725.94
... A42: P041 | B42: Highlighter Set | C42: Stationery | D42: 179 | E42: 115.83

Sheet Payment Method Analysis
A3: Row Labels | B3: Count of order_id
A4: Cash on Delivery | B4: 991
A5: Credit Card | B5: 1033
A6: Debit Card | B6: 981
A7: Net Banking | B7: 975
A8: UPI | B8: 1020
A9: Grand Total | B9: 5000

Sheet orders_cleaned
A1: order_id | B1: customer_id | C1: order_date | D1: payment_method | E1: order_status | F1: year | G1: month | H1: day | I1: month_name
A2: O000001 | B2: C00945 | C2: 46081 | D2: Debit Card | E2: Processing | F2: 2026 | G2: 2 | H2: 28 | I2: February | K2: Total Orders= | L2: =COUNTA(A2:A5001) -> 5000
A3: O000002 | B3: C00247 | C3: 45767 | D3: Cash on Delivery | E3: Delivered | F3: 2025 | G3: 4 | H3: 20 | I3: April
A4: O000003 | B4: C00907 | C4: 45882 | D4: Credit Card | E4: Delivered | F4: 2025 | G4: 8 | H4: 13 | I4: August
A5: O000004 | B5: C00772 | C5: 45990 | D5: Net Banking | E5: Shipped | F5: 2025 | G5: 11 | H5: 29 | I5: November
A6: O000005 | B6: C00227 | C6: 45668 | D6: Net Banking | E6: Returned | F6: 2025 | G6: 1 | H6: 11 | I6: January
A7: O000006 | B7: C00243 | C7: 46154 | D7: UPI | E7: Cancelled | F7: 2026 | G7: 5 | H7: 12 | I7: May
A8: O000007 | B8: C00211 | C8: 46237 | D8: UPI | E8: Processing | F8: 2026 | G8: 8 | H8: 3 | I8: August
A9: O000008 | B9: C00073 | C9: 46138 | D9: Net Banking | E9: Delivered | F9: 2026 | G9: 4 | H9: 26 | I9: April
A10: O000009 | B10: C00947 | C10: 46308 | D10: Cash on Delivery | E10: Processing | F10: 2026 | G10: 10 | H10: 13 | I10: October
A11: O000010 | B11: C00592 | C11: 45926 | D11: UPI | E11: Returned | F11: 2025 | G11: 9 | H11: 26 | I11: September
A12: O000011 | B12: C00490 | C12: 46060 | D12: Cash on Delivery | E12: Shipped | F12: 2026 | G12: 2 | H12: 7 | I12: February
A13: O000012 | B13: C00125 | C13: 45685 | D13: Credit Card | E13: Delivered | F13: 2025 | G13: 1 | H13: 28 | I13: January
A14: O000013 | B14: C00384 | C14: 45968 | D14: Debit Card | E14: Returned | F14: 2025 | G14: 11 | H14: 7 | I14: November
... A5001: O005000 | B5001: C00536 | C5001: 45876 | D5001: Debit Card | E5001: Shipped | F5001: 2025 | G5001: 8 | H5001: 7 | I5001: August

Sheet KPI_Summary
A1: E-Commerce Sales & Customer Analytics
A3: Column1 | B3: Column2
A4: Total Sales | B4: =SUM(order_items_cleaned!G2:G8346) -> 22630978
A5: Total Profit | B5: =SUM(order_items_cleaned!H2:H8346) -> 6373807.5
A6: Total Orders | B6: =COUNTA(orders_cleaned!A2:A5001) -> 5000
A7: Total Customers | B7: =COUNTA('customers_cleaned'!A2:A1001) -> 1000
A8: Total Products | B8: =COUNTA(products_cleaned!A2:A42) -> 41

Sheet customers_cleaned
A1: customer_id | B1: customer_name | C1: email | D1: city | E1: state | F1: signup_date | G1: customer_segment
A2: C00001 | B2: Aditi Shinde | C2: customer0001@example.com | D2: Navi Mumbai | E2: Maharashtra | F2: 45802 | G2: New
A3: C00002 | B3: Pooja Mane | C3: customer0002@example.com | D3: Navi Mumbai | E3: Maharashtra | F3: 45699 | G3: Premium
A4: C00003 | B4: Sana Mane | C4: customer0003@example.com | D4: Kolhapur | E4: Maharashtra | F4: 45817 | G4: Premium
A5: C00004 | B5: Aarav Shah | C5: customer0004@example.com | D5: Amravati | E5: Maharashtra | F5: 46076 | G5: New
A6: C00005 | B6: Sneha Chavan | C6: customer0005@example.com | D6: Jalgaon | E6: Maharashtra | F6: 45978 | G6: New
A7: C00006 | B7: Nikhil Khan | C7: customer0006@example.com | D7: Sangli | E7: Maharashtra | F7: 45773 | G7: New
A8: C00007 | B8: Ananya Kulkarni | C8: customer0007@example.com | D8: Aurangabad | E8: Maharashtra | F8: 45933 | G8: Premium
A9: C00008 | B9: Atharva Mane | C9: customer0008@example.com | D9: Aurangabad | E9: Maharashtra | F9: 46023 | G9: Premium
A10: C00009 | B10: Kunal Sane | C10: customer0009@example.com | D10: Kolhapur | E10: Maharashtra | F10: 45977 | G10: Regular
A11: C00010 | B11: Sakshi Chavan | C11: customer0010@example.com | D11: Satara | E11: Maharashtra | F11: 46007 | G11: Regular
A12: C00011 | B12: Aditya Khan | C12: customer0011@example.com | D12: Amravati | E12: Maharashtra | F12: 45499 | G12: Regular
A13: C00012 | B13: Meera Sharma | C13: customer0012@example.com | D13: Jalgaon | E13: Maharashtra | F13: 45325 | G13: New
... A1001: C01000 | B1001: Nikhil Pawar | C1001: customer1000@example.com | D1001: Mumbai | E1001: Maharashtra | F1001: 45680 | G1001: New

Sheet Pivot
A3: Row Labels | B3: Sum of sales_amount | C3: Sum of profit
A4: Books | B4: 1407710.6 | C4: 425086.17
A5: Electronics | B5: 5469410.6 | C5: 1631363.1
A6: Fashion | B6: 2876417.9 | C6: 658926.53
A7: Fitness | B7: 1126701.3 | C7: 271946.85
A8: Footwear | B8: 2713983.7 | C8: 557007.11
A9: Furniture | B9: 5051495.3 | C9: 1690475.5
A10: Home & Kitchen | B10: 3702522.8 | C10: 1050810.7
A11: Stationery | B11: 282735.91 | C11: 88191.61
A12: Grand Total | B12: 22630978 | C12: 6373807.5

Sheet Monthly Sales Trend Analysis
A3: Row Labels | B3: Sum of sales_amount
A4: January | B4: 2177368.7
A5: 1 | B5: 2177368.7
A6: February | B6: 1826203.5
A7: 2 | B7: 1826203.5
A8: March | B8: 2212557.1
A9: 3 | B9: 2212557.1
A10: April | B10: 2056392.4
A11: 4 | B11: 2056392.4
A12: May | B12: 2114838.7
A13: 5 | B13: 2114838.7
A14: June | B14: 2035713.7
A15: 6 | B15: 2035713.7
A16: July | B16: 2206418.3
A17: 7 | B17: 2206418.3
A18: August | B18: 2355987.3
A19: 8 | B19: 2355987.3
A20: September | B20: 1981701.2
A21: 9 | B21: 1981701.2
A22: October | B22: 1576576.6
A23: 10 | B23: 1576576.6
A24: November | B24: 1040407.2
A25: 11 | B25: 1040407.2
A26: December | B26: 1046813.3
A27: 12 | B27: 1046813.3
A28: Grand Total | B28: 22630978

Sheet order_items_cleaned
A1: order_item_id | B1: order_id | C1: product_id | D1: quantity | E1: unit_price | F1: discount_pct | G1: sales_amount | H1: profit | I1: Category | J1: Month | K1: Month_Number
A2: OI0000001 | B2: O000001 | C2: P033 | D2: 1 | E2: 1425.5 | F2: 0.1 | G2: 1282.95 | H2: 357.79 | I2: =VLOOKUP(C2,products_cleaned[[product_id]:[category]],3,) -> Furniture | J2: =VLOOKUP(B2,orders_cleaned!A:I,9,FALSE) -> February | K2: =MONTH(DATEVALUE("1"&J2)) -> 2
A3: OI0000002 | B3: O000002 | C3: P021 | D3: 1 | E3: 2784.34 | F3: 0.05 | G3: 2645.12 | H3: 523.05 | I3: =VLOOKUP(C3,products_cleaned[[product_id]:[category]],3,) -> Home & Kitchen | J3: =VLOOKUP(B3,orders_cleaned!A:I,9,FALSE) -> April | K3: =MONTH(DATEVALUE("1"&J3)) -> 4
A4: OI0000003 | B4: O000002 | C4: P037 | D4: 3 | E4: 235.8 | F4: 0 | G4: 707.4 | H4: 197.34 | I4: =VLOOKUP(C4,products_cleaned[[product_id]:[category]],3,) -> Fitness | J4: =VLOOKUP(B4,orders_cleaned!A:I,9,FALSE) -> April | K4: =MONTH(DATEVALUE("1"&J4)) -> 4
A5: OI0000004 | B5: O000003 | C5: P017 | D5: 1 | E5: 947.13 | F5: 0.15 | G5: 805.06 | H5: 287.71 | I5: =VLOOKUP(C5,products_cleaned[[product_id]:[category]],3,) -> Books | J5: =VLOOKUP(B5,orders_cleaned!A:I,9,FALSE) -> August | K5: =MONTH(DATEVALUE("1"&J5)) -> 8
A6: OI0000005 | B6: O000004 | C6: P005 | D6: 1 | E6: 4948.14 | F6: 0.1 | G6: 4453.33 | H6: 1815.31 | I6: =VLOOKUP(C6,products_cleaned[[product_id]:[category]],3,) -> Electronics | J6: =VLOOKUP(B6,orders_cleaned!A:I,9,FALSE) -> November | K6: =MONTH(DATEVALUE("1"&J6)) -> 11
A7: OI0000006 | B7: O000005 | C7: P017 | D7: 1 | E7: 900.41 | F7: 0.2 | G7: 720.33 | H7: 202.98 | I7: =VLOOKUP(C7,products_cleaned[[product_id]:[category]],3,) -> Books | J7: =VLOOKUP(B7,orders_cleaned!A:I,9,FALSE) -> January | K7: =MONTH(DATEVALUE("1"&J7)) -> 1
A8: OI0000007 | B8: O000005 | C8: P014 | D8: 1 | E8: 875.16 | F8: 0.1 | G8: 787.64 | H8: 171.92 | I8: =VLOOKUP(C8,products_cleaned[[product_id]:[category]],3,) -> Fashion | J8: =VLOOKUP(B8,orders_cleaned!A:I,9,FALSE) -> January | K8: =MONTH(DATEVALUE("1"&J8)) -> 1
A9: OI0000008 | B9: O000006 | C9: P025 | D9: 1 | E9: 430.34 | F9: 0 | G9: 430.34 | H9: 120.96 | I9: =VLOOKUP(C9,products_cleaned[[product_id]:[category]],3,) -> Home & Kitchen | J9: =VLOOKUP(B9,orders_cleaned!A:I,9,FALSE) -> May | K9: =MONTH(DATEVALUE("1"&J9)) -> 5
A10: OI0000009 | B10: O000007 | C10: P016 | D10: 1 | E10: 526.67 | F10: 0.05 | G10: 500.34 | H10: 155.4 | I10: =VLOOKUP(C10,products_cleaned[[product_id]:[category]],3,) -> Books | J10: =VLOOKUP(B10,orders_cleaned!A:I,9,FALSE) -> August | K10: =MONTH(DATEVALUE("1"&J10)) -> 8
A11: OI0000010 | B11: O000008 | C11: P025 | D11: 4 | E11: 427.37 | F11: 0.2 | G11: 1367.58 | H11: 130.06 | I11: =VLOOKUP(C11,products_cleaned[[product_id]:[category]],3,) -> Home & Kitchen | J11: =VLOOKUP(B11,orders_cleaned!A:I,9,FALSE) -> April | K11: =MONTH(DATEVALUE("1"&J11)) -> 4
A12: OI0000011 | B12: O000008 | C12: P016 | D12: 2 | E12: 524.64 | F12: 0.15 | G12: 891.89 | H12: 202.01 | I12: =VLOOKUP(C12,products_cleaned[[product_id]:[category]],3,) -> Books | J12: =VLOOKUP(B12,orders_cleaned!A:I,9,FALSE) -> April | K12: =MONTH(DATEVALUE("1"&J12)) -> 4
A13: OI0000012 | B13: O000009 | C13: P004 | D13: 2 | E13: 1210.72 | F13: 0.2 | G13: 1937.15 | H13: -5.63 | I13: =VLOOKUP(C13,products_cleaned[[product_id]:[category]],3,) -> Electronics | J13: =VLOOKUP(B13,orders_cleaned!A:I,9,FALSE) -> October | K13: =MONTH(DATEVALUE("1"&J13)) -> 10
... A8346: OI0008345 | B8346: O005000 | C8346: P005 | D8346: 3 | E8346: 4515.94 | F8346: 0.05 | G8346: 12870.43 | H8346: 4956.37 | I8346: =VLOOKUP(C8346,products_cleaned[[product_id]:[category]],3,) -> Electronics | J8346: =VLOOKUP(B8346,orders_cleaned!A:I,9,FALSE) -> August | K8346: =MONTH(DATEVALUE("1"&J8346)) -> 8
F8348: Total Sales= | G8348: =SUM(G2:G8346) -> 22630978
F8350: Total Profit= | G8350: =SUM(H2:H8346) -> 6373807.5
